pymagicstrip/__init__.py
pymagicstrip/const.py
pymagicstrip/errors.py
pymagicstrip-0.1.0.dist-info/LICENSE
pymagicstrip-0.1.0.dist-info/METADATA
pymagicstrip-0.1.0.dist-info/WHEEL
pymagicstrip-0.1.0.dist-info/top_level.txt
pymagicstrip-0.1.0.dist-info/zip-safe
pymagicstrip-0.1.0.dist-info/RECORD
