Metadata-Version: 2.1
Name: pymagicstrip
Version: 0.1.0
Summary: Python Interface for Magic Strip LED Controllers
Home-page: https://github.com/elahd/pymagicstrip
Author: Elahd Bar-Shai
Author-email: 
License: MIT
Keywords: Magic Strip
Platform: UNKNOWN
Classifier: Development Status :: 4 - Beta
Classifier: Natural Language :: English
Classifier: Environment :: Web Environment
Classifier: Intended Audience :: Developers
Classifier: Programming Language :: Python :: 3
Classifier: License :: OSI Approved :: MIT License
Classifier: Operating System :: OS Independent
Classifier: Topic :: Software Development :: Libraries :: Python Modules
Classifier: Topic :: Home Automation
Requires-Python: >=3.9
License-File: LICENSE
Requires-Dist: bleak (==0.14.2)
